tiny_eval-0.1.0.dist-info/METADATA
tiny_eval-0.1.0.dist-info/WHEEL
tiny_eval-0.1.0.dist-info/entry_points.txt
tiny_eval/__init__.py
tiny_eval/core/_types.py
tiny_eval/core/constants.py
tiny_eval/model_api/__init__.py
tiny_eval/model_api/base.py
tiny_eval/model_api/builder.py
tiny_eval/model_api/fireworks.py
tiny_eval/model_api/openai.py
tiny_eval/model_api/wrapper.py
tiny_eval/utils/asyncio.py
tiny_eval/utils/jsonl.py
tiny_eval/utils/logprobs.py
tiny_eval-0.1.0.dist-info/RECORD
