Metadata-Version: 2.1
Name: tiny-eval
Version: 0.1.0
Summary: TinyEval: A tiny evaluation framework for language models
Author-Email: Daniel Tan <dtch1997@users.noreply.github.com>
License: MIT
Requires-Python: >=3.11
Requires-Dist: openrouter>=1.0
Requires-Dist: python-dotenv>=1.0.1
Requires-Dist: openai>=1.60.1
Requires-Dist: ipykernel>=6.29.5
Requires-Dist: backoff>=2.2.1
Requires-Dist: fireworks-ai>=0.15.12
Provides-Extra: experiments
Requires-Dist: pandas>=2.2.3; extra == "experiments"
Requires-Dist: streamlit>=1.41.1; extra == "experiments"
Requires-Dist: matplotlib>=3.10.0; extra == "experiments"
Requires-Dist: seaborn>=0.13.2; extra == "experiments"
Requires-Dist: plotly>=6.0.0; extra == "experiments"
Provides-Extra: dev
Requires-Dist: pytest>=8.3.4; extra == "dev"
Requires-Dist: pytest-asyncio>=0.25.3; extra == "dev"
Requires-Dist: pyright>=1.1.393; extra == "dev"
